ambit_fe/__init__.py
ambit_fe/ambit_main.py
ambit_fe/base.py
ambit_fe/boundaryconditions.py
ambit_fe/expression.py
ambit_fe/ioparams.py
ambit_fe/ioroutines.py
ambit_fe/mathutils.py
ambit_fe/meshutils.py
ambit_fe/mpiroutines.py
ambit_fe/oderoutines.py
ambit_fe/resultcheck.py
ambit_fe/timeintegration.py
ambit_fe/utilities.py
ambit_fe/variationalform.py
ambit_fe/ale/__init__.py
ambit_fe/ale/ale_kinematics_constitutive.py
ambit_fe/ale/ale_main.py
ambit_fe/ale/ale_material.py
ambit_fe/ale/ale_variationalform.py
ambit_fe/coupling/__init__.py
ambit_fe/coupling/fluid_ale_constraint_main.py
ambit_fe/coupling/fluid_ale_flow0d_main.py
ambit_fe/coupling/fluid_ale_main.py
ambit_fe/coupling/fluid_constraint_main.py
ambit_fe/coupling/fluid_flow0d_main.py
ambit_fe/coupling/fsi_flow0d_main.py
ambit_fe/coupling/fsi_main.py
ambit_fe/coupling/solid_constraint_main.py
ambit_fe/coupling/solid_flow0d_main.py
ambit_fe/coupling/solid_flow0d_periodicref_main.py
ambit_fe/electrophysiology/electrophysiology_constitutive.py
ambit_fe/electrophysiology/electrophysiology_main.py
ambit_fe/electrophysiology/electrophysiology_variationalform.py
ambit_fe/flow0d/__init__.py
ambit_fe/flow0d/cardiovascular0D.py
ambit_fe/flow0d/cardiovascular0D_2elwindkessel.py
ambit_fe/flow0d/cardiovascular0D_4elwindkesselLpZ.py
ambit_fe/flow0d/cardiovascular0D_4elwindkesselLsZ.py
ambit_fe/flow0d/cardiovascular0D_CRLinoutlink.py
ambit_fe/flow0d/cardiovascular0D_coronary.py
ambit_fe/flow0d/cardiovascular0D_syspul.py
ambit_fe/flow0d/cardiovascular0D_syspulcap.py
ambit_fe/flow0d/cardiovascular0D_syspulcaprespir.py
ambit_fe/flow0d/cardiovascular0D_vad.py
ambit_fe/flow0d/flow0d_main.py
ambit_fe/fluid/__init__.py
ambit_fe/fluid/fluid_kinematics_constitutive.py
ambit_fe/fluid/fluid_main.py
ambit_fe/fluid/fluid_material.py
ambit_fe/fluid/fluid_variationalform.py
ambit_fe/mor/__init__.py
ambit_fe/mor/mor_main.py
ambit_fe/multiscale/__init__.py
ambit_fe/multiscale/solid_flow0d_growthremodel_main.py
ambit_fe-1.3.dist-info/LICENSE
ambit_fe-1.3.dist-info/METADATA
ambit_fe-1.3.dist-info/WHEEL
ambit_fe-1.3.dist-info/top_level.txt
ambit_fe-1.3.dist-info/RECORD
