Metadata-Version: 2.1
Name: ambit-fe
Version: 1.3
Summary: A FEniCS-based cardiovascular multi-physics solver
Author-email: Marc Hirschvogel <marc.hirschvogel@ambit.net>
License: MIT License
Project-URL: Homepage, https://github.com/marchirschvogel/ambit
Project-URL: Bug Tracker, https://github.com/marchirschvogel/ambit/issues
Keywords: finite elements,solid mechanics,fluid mechanics,fluid-solid interaction,fsi,0D models,3D-0D coupling,monolithic,lumped-parameter models,model reduction,heart,circulation,cardiac
License-File: LICENSE
Requires-Dist: mpmath
Requires-Dist: sympy
